Metadata-Version: 1.1
Name: orthoproj
Version: 0.0.3
Summary: Python package to create an Orthogonal Projection of 3D data with full axes synchronisation
Home-page: https://github.com/apbard/orthoproj
Author: Alessandro Pietro Bardelli
Author-email: UNKNOWN
License: MIT
Keywords: orthogonal projections,visualisation,plot
Platform: UNKNOWN
Classifier: Development Status :: 4 - Beta
Classifier: Intended Audience :: Science/Research
Classifier: Topic :: Scientific/Engineering :: Visualization
Classifier: License :: OSI Approved :: MIT License
Classifier: Programming Language :: Python
Classifier: Programming Language :: Python :: 2
Classifier: Programming Language :: Python :: 3
